wikicat/__init__.py
wikicat/constants.py
wikicat/version.py
wikicat/processing/__init__.py
wikicat/processing/download_dump.py
wikicat/processing/generate_graph.py
wikicat/processing/merge_tables.py
wikicat/processing/process_dump.py
wikicat/viewer/__init__.py
wikicat/viewer/__main__.py
wikicat/viewer/components.py
wikicat/viewer/utils.py
wikicat-0.0.1.dev8.dist-info/LICENSE
wikicat-0.0.1.dev8.dist-info/METADATA
wikicat-0.0.1.dev8.dist-info/WHEEL
wikicat-0.0.1.dev8.dist-info/top_level.txt
wikicat-0.0.1.dev8.dist-info/RECORD
