Metadata-Version: 2.1
Name: wikicat
Version: 0.0.1.dev8
Summary: Toolkit for managing and navigating graphs of Wikipedia categories
Home-page: https://xhluca.github.io/wikicat
Author: Xing Han Lu, Aristides Milios
Author-email: wikicat@xinghanlu.com
License: MIT
Requires-Python: >=3.7
License-File: LICENSE
Provides-Extra: dev
Requires-Dist: black (==23.*) ; extra == 'dev'
Requires-Dist: wheel ; extra == 'dev'
Provides-Extra: processing
Requires-Dist: pandas ; extra == 'processing'
Requires-Dist: kwnlp-sql-parser (==0.0.1) ; extra == 'processing'
Provides-Extra: viewer
Requires-Dist: dash (>=2.7) ; extra == 'viewer'
Requires-Dist: dash-bootstrap-components (>=1.2) ; extra == 'viewer'
Requires-Dist: dash-cytoscape (>=0.2.4) ; extra == 'viewer'
Requires-Dist: gunicorn ; extra == 'viewer'
